odoo/addons/l10n_br_base/README.rst
odoo/addons/l10n_br_base/__init__.py
odoo/addons/l10n_br_base/__manifest__.py
odoo/addons/l10n_br_base/hooks.py
odoo/addons/l10n_br_base/data/res.bank.csv
odoo/addons/l10n_br_base/data/res.city.csv
odoo/addons/l10n_br_base/data/res.country.state.csv
odoo/addons/l10n_br_base/data/res_country_data.xml
odoo/addons/l10n_br_base/demo/l10n_br_base_demo.xml
odoo/addons/l10n_br_base/demo/res_company_demo.xml
odoo/addons/l10n_br_base/demo/res_partner_demo.xml
odoo/addons/l10n_br_base/demo/res_users_demo.xml
odoo/addons/l10n_br_base/i18n/l10n_br_base.pot
odoo/addons/l10n_br_base/i18n/pt_BR.po
odoo/addons/l10n_br_base/migrations/13.0.2.0.0/pre-migration.py
odoo/addons/l10n_br_base/models/__init__.py
odoo/addons/l10n_br_base/models/party_mixin.py
odoo/addons/l10n_br_base/models/res_bank.py
odoo/addons/l10n_br_base/models/res_city.py
odoo/addons/l10n_br_base/models/res_company.py
odoo/addons/l10n_br_base/models/res_config_settings.py
odoo/addons/l10n_br_base/models/res_country.py
odoo/addons/l10n_br_base/models/res_country_state.py
odoo/addons/l10n_br_base/models/res_partner.py
odoo/addons/l10n_br_base/models/res_partner_bank.py
odoo/addons/l10n_br_base/models/state_tax_numbers.py
odoo/addons/l10n_br_base/readme/CONFIGURE.rst
odoo/addons/l10n_br_base/readme/CONTRIBUTORS.rst
odoo/addons/l10n_br_base/readme/DESCRIPTION.rst
odoo/addons/l10n_br_base/readme/HISTORY.rst
odoo/addons/l10n_br_base/readme/INSTALL.rst
odoo/addons/l10n_br_base/readme/ROADMAP.rst
odoo/addons/l10n_br_base/readme/USAGE.rst
odoo/addons/l10n_br_base/security/ir.model.access.csv
odoo/addons/l10n_br_base/static/description/icon.png
odoo/addons/l10n_br_base/static/description/index.html
odoo/addons/l10n_br_base/static/img/res_partner_akretion-image.jpg
odoo/addons/l10n_br_base/static/img/res_partner_kmee.png
odoo/addons/l10n_br_base/static/src/less/form_view.less
odoo/addons/l10n_br_base/tests/__init__.py
odoo/addons/l10n_br_base/tests/test_amount_to_text.py
odoo13_addon_l10n_br_base-13.0.2.0.1.dev2.dist-info/METADATA
odoo13_addon_l10n_br_base-13.0.2.0.1.dev2.dist-info/WHEEL
odoo13_addon_l10n_br_base-13.0.2.0.1.dev2.dist-info/top_level.txt
odoo13_addon_l10n_br_base-13.0.2.0.1.dev2.dist-info/RECORD
