Metadata-Version: 2.1
Name: odoo13-addon-l10n-br-base
Version: 13.0.2.0.1.dev2
Summary: Customization of base module for implementations in Brazil.
Home-page: https://github.com/OCA/l10n-brazil
Author: Akretion,Odoo Community Association (OCA)
Author-email: support@odoo-community.org
License: AGPL-3
Platform: UNKNOWN
Classifier: Programming Language :: Python
Classifier: Framework :: Odoo
Classifier: Framework :: Odoo :: 13.0
Classifier: License :: OSI Approved :: GNU Affero General Public License v3
Classifier: Development Status :: 6 - Mature
Requires-Python: >=3.5
Requires-Dist: erpbrasil.base
Requires-Dist: num2words
Requires-Dist: odoo <13.1dev,>=13.0a
